envelope/__init__.py
envelope/admin.py
envelope/apps.py
envelope/async_signals.py
envelope/decorators.py
envelope/envelopes.py
envelope/logging.py
envelope/models.py
envelope/registries.py
envelope/schemas.py
envelope/signals.py
envelope/testing.py
envelope/utils.py
envelope/app/__init__.py
envelope/app/online_channel/__init__.py
envelope/app/online_channel/apps.py
envelope/app/online_channel/async_signals.py
envelope/app/online_channel/channel.py
envelope/app/user_channel/__init__.py
envelope/app/user_channel/apps.py
envelope/app/user_channel/async_signals.py
envelope/app/user_channel/channel.py
envelope/app/user_channel/signals.py
envelope/channels/__init__.py
envelope/channels/decorators.py
envelope/channels/errors.py
envelope/channels/messages.py
envelope/channels/models.py
envelope/channels/schemas.py
envelope/channels/testing.py
envelope/channels/utils.py
envelope/consumers/__init__.py
envelope/consumers/utils.py
envelope/consumers/websocket.py
envelope/core/__init__.py
envelope/core/async_signals.py
envelope/core/envelope.py
envelope/core/message.py
envelope/core/transport.py
envelope/deferred_jobs/__init__.py
envelope/deferred_jobs/async_signals.py
envelope/deferred_jobs/jobs.py
envelope/deferred_jobs/message.py
envelope/messages/__init__.py
envelope/messages/common.py
envelope/messages/errors.py
envelope/messages/ping.py
envelope/messages/testing.py
envelope/migrations/0001_initial.py
envelope/migrations/0002_auto_20211214_1327.py
envelope/migrations/__init__.py
channels_envelope-1.1.0.dist-info/LICENSE
channels_envelope-1.1.0.dist-info/METADATA
channels_envelope-1.1.0.dist-info/WHEEL
channels_envelope-1.1.0.dist-info/top_level.txt
channels_envelope-1.1.0.dist-info/RECORD
