Metadata-Version: 2.1
Name: channels-envelope
Version: 1.1.0
Summary: Message handling for Django channels
Author-email: VoteIT dev team <info@voteit.se>
Project-URL: Homepage, https://github.com/VoteIT/channels_envelope
Project-URL: Issues, https://github.com/VoteIT/channels_envelope/issues
Project-URL: Changelog, https://github.com/VoteIT/channels_envelope/blob/main/CHANGELOG.md
Classifier: Framework :: Django
Classifier: Intended Audience :: Developers
Classifier: Programming Language :: Python :: 3
Classifier: License :: OSI Approved :: GNU General Public License v3 (GPLv3)
Classifier: Operating System :: POSIX
Requires-Python: >=3.10
License-File: LICENSE
Requires-Dist: channels[daphne]
Requires-Dist: django
Requires-Dist: django-rq
Requires-Dist: rq
Requires-Dist: pydantic <2
Requires-Dist: async-signals
